opencv_toasty_animation/__init__.py
opencv_toasty_animation/animation.py
opencv_toasty_animation/toasty.mp3
opencv_toasty_animation/toasty.png
opencv_toasty_animation/toasty.py
opencv_toasty_animation-0.0.1.dist-info/LICENSE
opencv_toasty_animation-0.0.1.dist-info/METADATA
opencv_toasty_animation-0.0.1.dist-info/WHEEL
opencv_toasty_animation-0.0.1.dist-info/entry_points.txt
opencv_toasty_animation-0.0.1.dist-info/top_level.txt
opencv_toasty_animation-0.0.1.dist-info/RECORD
