Metadata-Version: 2.1
Name: opencv-toasty-animation
Version: 0.0.1
Summary: Toasty animation to play in top of OpenCV VideoCapture
Home-page: https://github.com/adremides/python_opencv_toasty_animation
Author: Yamil Jaskolowski
Author-email: yamilj@gmail.com
License: GPLv3
Project-URL: Issue Tracker, https://github.com/adremides/python_opencv_toasty_animation/issues
Keywords: opencv,animation,VideoCapture,toasty
Classifier: Intended Audience :: Developers
Classifier: License :: OSI Approved :: GNU General Public License v3 or later (GPLv3+)
Classifier: Operating System :: OS Independent
Classifier: Programming Language :: Python :: 3
Classifier: Topic :: Software Development :: Libraries :: Python Modules
Classifier: Topic :: Utilities
Requires-Python: >=3.10
License-File: LICENSE
Requires-Dist: setuptools
Requires-Dist: importlib-resources
Requires-Dist: opencv-contrib-python
Requires-Dist: playsound
